keras_lmu/__init__.py
keras_lmu/layers.py
keras_lmu/version.py
keras_lmu/tests/__init__.py
keras_lmu/tests/conftest.py
keras_lmu/tests/test_benchmarks.py
keras_lmu/tests/test_layers.py
keras_lmu-0.8.0.dist-info/licenses/LICENSE.rst
keras_lmu-0.8.0.dist-info/METADATA
keras_lmu-0.8.0.dist-info/WHEEL
keras_lmu-0.8.0.dist-info/top_level.txt
keras_lmu-0.8.0.dist-info/RECORD
